[
  {
    "id": "it_e_001",
    "text": "CASA AL MARE",
    "hint": "Vacanza estiva",
    "language": "it",
    "difficulty": "easy",
    "category": "common"
  },
  {
    "id": "it_e_002",
    "text": "TEMPO SERENO",
    "hint": "Bel clima",
    "language": "it",
    "difficulty": "easy",
    "category": "nature"
  },
  {
    "id": "it_e_003",
    "text": "BUON APPETITO",
    "hint": "Si dice prima di mangiare",
    "language": "it",
    "difficulty": "easy",
    "category": "common"
  },
  {
    "id": "it_e_004",
    "text": "LUNA PIENA",
    "hint": "Fase lunare",
    "language": "it",
    "difficulty": "easy",
    "category": "nature"
  },
  {
    "id": "it_e_005",
    "text": "MARE CALMO",
    "hint": "Acqua tranquilla",
    "language": "it",
    "difficulty": "easy",
    "category": "nature"
  },
  {
    "id": "it_e_006",
    "text": "PORTA APERTA",
    "hint": "Accesso libero",
    "language": "it",
    "difficulty": "easy",
    "category": "object"
  },
  {
    "id": "it_e_007",
    "text": "SOLE NASCENTE",
    "hint": "Momento dell alba",
    "language": "it",
    "difficulty": "easy",
    "category": "nature"
  },
  {
    "id": "it_e_008",
    "text": "VITA NUOVA",
    "hint": "Nuovo inizio",
    "language": "it",
    "difficulty": "easy",
    "category": "abstract"
  },
  {
    "id": "it_e_009",
    "text": "GATTO NERO",
    "hint": "Animale domestico",
    "language": "it",
    "difficulty": "easy",
    "category": "animal"
  },
  {
    "id": "it_e_010",
    "text": "BUON ANNO",
    "hint": "Augurio di gennaio",
    "language": "it",
    "difficulty": "easy",
    "category": "event"
  },
  {
    "id": "it_e_011",
    "text": "ARIA FRESCA",
    "hint": "Clima piacevole",
    "language": "it",
    "difficulty": "easy",
    "category": "nature"
  },
  {
    "id": "it_e_012",
    "text": "LIBRO APERTO",
    "hint": "Oggetto da leggere",
    "language": "it",
    "difficulty": "easy",
    "category": "object"
  },
  {
    "id": "it_e_013",
    "text": "STRADA LUNGA",
    "hint": "Percorso esteso",
    "language": "it",
    "difficulty": "easy",
    "category": "common"
  },
  {
    "id": "it_e_014",
    "text": "CUORE CONTENTO",
    "hint": "Emozione positiva",
    "language": "it",
    "difficulty": "easy",
    "category": "emotion"
  },
  {
    "id": "it_e_015",
    "text": "FIUME LENTO",
    "hint": "Corso dacqua",
    "language": "it",
    "difficulty": "easy",
    "category": "nature"
  },
  {
    "id": "it_e_016",
    "text": "NEVE BIANCA",
    "hint": "Precipitazione invernale",
    "language": "it",
    "difficulty": "easy",
    "category": "nature"
  },
  {
    "id": "it_e_017",
    "text": "MANO AMICA",
    "hint": "Aiuto sincero",
    "language": "it",
    "difficulty": "easy",
    "category": "abstract"
  },
  {
    "id": "it_e_018",
    "text": "SOGNI DORO",
    "hint": "Augurio notturno",
    "language": "it",
    "difficulty": "easy",
    "category": "common"
  },
  {
    "id": "it_e_019",
    "text": "CAMPO VERDE",
    "hint": "Prato",
    "language": "it",
    "difficulty": "easy",
    "category": "nature"
  },
  {
    "id": "it_e_020",
    "text": "FESTA GRANDE",
    "hint": "Evento importante",
    "language": "it",
    "difficulty": "easy",
    "category": "event"
  },
  {
    "id": "it_e_021",
    "text": "TEMPO LIBERO",
    "hint": "Momento senza lavoro",
    "language": "it",
    "difficulty": "easy",
    "category": "common"
  },
  {
    "id": "it_e_022",
    "text": "SALA PIENA",
    "hint": "Ambiente affollato",
    "language": "it",
    "difficulty": "easy",
    "category": "common"
  },
  {
    "id": "it_e_023",
    "text": "CIELO AZZURRO",
    "hint": "Giornata limpida",
    "language": "it",
    "difficulty": "easy",
    "category": "nature"
  },
  {
    "id": "it_e_024",
    "text": "LUCE ACCESA",
    "hint": "Illuminazione",
    "language": "it",
    "difficulty": "easy",
    "category": "object"
  },
  {
    "id": "it_e_025",
    "text": "PORTA CHIUSA",
    "hint": "Accesso negato",
    "language": "it",
    "difficulty": "easy",
    "category": "object"
  },
  {
    "id": "it_e_026",
    "text": "VINO ROSSO",
    "hint": "Bevanda italiana",
    "language": "it",
    "difficulty": "easy",
    "category": "food"
  },
  {
    "id": "it_e_027",
    "text": "PANE CALDO",
    "hint": "Appena sfornato",
    "language": "it",
    "difficulty": "easy",
    "category": "food"
  },
  {
    "id": "it_e_028",
    "text": "GIORNO LUNGO",
    "hint": "Durata estesa",
    "language": "it",
    "difficulty": "easy",
    "category": "time"
  },
  {
    "id": "it_e_029",
    "text": "OCCHI AZZURRI",
    "hint": "Colore particolare",
    "language": "it",
    "difficulty": "easy",
    "category": "people"
  },
  {
    "id": "it_e_030",
    "text": "NOTTE CALMA",
    "hint": "Assenza di rumore",
    "language": "it",
    "difficulty": "easy",
    "category": "common"
  },
  {
    "id": "it_m_001",
    "text": "CHI LA DURA LA VINCE",
    "hint": "Proverbio sulla perseveranza",
    "language": "it",
    "difficulty": "medium",
    "category": "proverb"
  },
  {
    "id": "it_m_002",
    "text": "MEGLIO TARDI CHE MAI",
    "hint": "Proverbio sul tempo",
    "language": "it",
    "difficulty": "medium",
    "category": "proverb"
  },
  {
    "id": "it_m_003",
    "text": "LA VITA E BELLA",
    "hint": "Film italiano premio Oscar",
    "language": "it",
    "difficulty": "medium",
    "category": "movie"
  },
  {
    "id": "it_m_004",
    "text": "VOLARE OH OH",
    "hint": "Canzone italiana famosa",
    "language": "it",
    "difficulty": "medium",
    "category": "music"
  },
  {
    "id": "it_m_005",
    "text": "ACQUA IN BOCCA",
    "hint": "Invito al silenzio",
    "language": "it",
    "difficulty": "medium",
    "category": "idiom"
  },
  {
    "id": "it_m_006",
    "text": "STRADA SENZA USCITA",
    "hint": "Vicoli ciechi",
    "language": "it",
    "difficulty": "medium",
    "category": "common"
  },
  {
    "id": "it_m_007",
    "text": "LUCE IN FONDO AL TUNNEL",
    "hint": "Segno di speranza",
    "language": "it",
    "difficulty": "medium",
    "category": "idiom"
  },
  {
    "id": "it_m_008",
    "text": "IL NOME DELLA ROSA",
    "hint": "Romanzo di Eco",
    "language": "it",
    "difficulty": "medium",
    "category": "literature"
  },
  {
    "id": "it_m_009",
    "text": "OCCHIO NON VEDE CUORE NON DUOLE",
    "hint": "Proverbio famoso",
    "language": "it",
    "difficulty": "medium",
    "category": "proverb"
  },
  {
    "id": "it_m_010",
    "text": "CHI TROVA UN AMICO TROVA UN TESORO",
    "hint": "Proverbio sull amicizia",
    "language": "it",
    "difficulty": "medium",
    "category": "proverb"
  },
  {
    "id": "it_m_011",
    "text": "EFFETTO DOMINO",
    "hint": "Reazione a catena",
    "language": "it",
    "difficulty": "medium",
    "category": "science"
  },
  {
    "id": "it_m_012",
    "text": "PUNTO DI NON RITORNO",
    "hint": "Momento decisivo",
    "language": "it",
    "difficulty": "medium",
    "category": "common"
  },
  {
    "id": "it_m_013",
    "text": "LA DOLCE VITA",
    "hint": "Film di Fellini",
    "language": "it",
    "difficulty": "medium",
    "category": "movie"
  },
  {
    "id": "it_m_014",
    "text": "IL CIELO IN UNA STANZA",
    "hint": "Canzone italiana",
    "language": "it",
    "difficulty": "medium",
    "category": "music"
  },
  {
    "id": "it_m_015",
    "text": "AMARCORD DI FELLINI",
    "hint": "Film italiano",
    "language": "it",
    "difficulty": "medium",
    "category": "movie"
  },
  {
    "id": "it_m_016",
    "text": "SPIRITO DI SQUADRA",
    "hint": "Collaborazione",
    "language": "it",
    "difficulty": "medium",
    "category": "common"
  },
  {
    "id": "it_m_017",
    "text": "NOTTE PRIMA DEGLI ESAMI",
    "hint": "Canzone italiana",
    "language": "it",
    "difficulty": "medium",
    "category": "music"
  },
  {
    "id": "it_m_018",
    "text": "IL POSTO DELLE FRAGOLE",
    "hint": "Film di Bergman",
    "language": "it",
    "difficulty": "medium",
    "category": "movie"
  },
  {
    "id": "it_m_019",
    "text": "IL VECCHIO E IL MARE",
    "hint": "Romanzo di Hemingway",
    "language": "it",
    "difficulty": "medium",
    "category": "literature"
  },
  {
    "id": "it_m_020",
    "text": "IL GATTOPARDO DI LAMPEDUSA",
    "hint": "Romanzo storico",
    "language": "it",
    "difficulty": "medium",
    "category": "literature"
  },
  {
    "id": "it_m_021",
    "text": "SOGNO DI UNA NOTTE DI MEZZA ESTATE",
    "hint": "Opera di Shakespeare",
    "language": "it",
    "difficulty": "medium",
    "category": "literature"
  },
  {
    "id": "it_m_022",
    "text": "IL BUONO IL BRUTTO E IL CATTIVO",
    "hint": "Film western italiano",
    "language": "it",
    "difficulty": "medium",
    "category": "movie"
  },
  {
    "id": "it_m_023",
    "text": "LA COSCIENZA DI ZENO",
    "hint": "Romanzo italiano",
    "language": "it",
    "difficulty": "medium",
    "category": "literature"
  },
  {
    "id": "it_m_024",
    "text": "L OCCHIO DEL TIGRE",
    "hint": "Canzone rock famosa",
    "language": "it",
    "difficulty": "medium",
    "category": "music"
  },
  {
    "id": "it_m_025",
    "text": "IL SIGNORE DEGLI ANELLI",
    "hint": "Saga fantasy",
    "language": "it",
    "difficulty": "medium",
    "category": "literature"
  },
  {
    "id": "it_m_026",
    "text": "UNA GIORNATA PARTICOLARE",
    "hint": "Film italiano",
    "language": "it",
    "difficulty": "medium",
    "category": "movie"
  },
  {
    "id": "it_m_027",
    "text": "C ERA UNA VOLTA IN AMERICA",
    "hint": "Film di Leone",
    "language": "it",
    "difficulty": "medium",
    "category": "movie"
  },
  {
    "id": "it_m_028",
    "text": "IL SILENZIO STAMPA",
    "hint": "Ordine ai giornalisti",
    "language": "it",
    "difficulty": "medium",
    "category": "common"
  },
  {
    "id": "it_m_029",
    "text": "IL GRANDE GATSBY",
    "hint": "Romanzo americano",
    "language": "it",
    "difficulty": "medium",
    "category": "literature"
  },
  {
    "id": "it_m_030",
    "text": "PER UN PUGNO DI DOLLARI",
    "hint": "Film western",
    "language": "it",
    "difficulty": "medium",
    "category": "movie"
  },
  {
    "id": "it_h_001",
    "text": "CHI SEMINA VENTO RACCOGLIE TEMPESTA",
    "hint": "Proverbio sulle conseguenze",
    "language": "it",
    "difficulty": "hard",
    "category": "proverb"
  },
  {
    "id": "it_h_002",
    "text": "NON TUTTI I MALI VENGONO PER NUOCERE",
    "hint": "Proverbio positivo",
    "language": "it",
    "difficulty": "hard",
    "category": "proverb"
  },
  {
    "id": "it_h_003",
    "text": "LA VERITA STA NEL MEZZO",
    "hint": "Espressione filosofica",
    "language": "it",
    "difficulty": "hard",
    "category": "philosophy"
  },
  {
    "id": "it_h_004",
    "text": "IL MONDO COME VOLONTA E RAPPRESENTAZIONE",
    "hint": "Opera di Schopenhauer",
    "language": "it",
    "difficulty": "hard",
    "category": "philosophy"
  },
  {
    "id": "it_h_005",
    "text": "LA TEORIA DELLA RELATIVITA GENERALE",
    "hint": "Concetto di Einstein",
    "language": "it",
    "difficulty": "hard",
    "category": "science"
  },
  {
    "id": "it_h_006",
    "text": "IL SILENZIO DEGLI INNOCENTI",
    "hint": "Film thriller famoso",
    "language": "it",
    "difficulty": "hard",
    "category": "movie"
  },
  {
    "id": "it_h_007",
    "text": "PER ASPERA AD ASTRA SEMPRE AVANTI",
    "hint": "Motto latino esteso",
    "language": "it",
    "difficulty": "hard",
    "category": "latin"
  },
  {
    "id": "it_h_008",
    "text": "UNA QUESTIONE DI PRINCIPIO MORALE",
    "hint": "Riguarda valori etici",
    "language": "it",
    "difficulty": "hard",
    "category": "abstract"
  },
  {
    "id": "it_h_009",
    "text": "CHI NON RISCHIA NON OTTIENE NULLA",
    "hint": "Proverbio motivazionale",
    "language": "it",
    "difficulty": "hard",
    "category": "proverb"
  },
  {
    "id": "it_h_010",
    "text": "IL PIACERE DI ESSERE E DI APPARIRE",
    "hint": "Tema esistenziale",
    "language": "it",
    "difficulty": "hard",
    "category": "philosophy"
  },
  {
    "id": "it_h_011",
    "text": "IL CURIOSO CASO DI BENJAMIN BUTTON",
    "hint": "Film particolare",
    "language": "it",
    "difficulty": "hard",
    "category": "movie"
  },
  {
    "id": "it_h_012",
    "text": "IL TRENO DEI DESIDERI NEI MIEI PENSIERI",
    "hint": "Verso musicale",
    "language": "it",
    "difficulty": "hard",
    "category": "music"
  },
  {
    "id": "it_h_013",
    "text": "IL CODICE DA VINCI DI DAN BROWN",
    "hint": "Romanzo bestseller",
    "language": "it",
    "difficulty": "hard",
    "category": "literature"
  },
  {
    "id": "it_h_014",
    "text": "IL NOME DELLA ROSA DI ECO",
    "hint": "Romanzo medievale",
    "language": "it",
    "difficulty": "hard",
    "category": "literature"
  },
  {
    "id": "it_h_015",
    "text": "UNA NOTTE DA LEONI A LAS VEGAS",
    "hint": "Film comico",
    "language": "it",
    "difficulty": "hard",
    "category": "movie"
  },
  {
    "id": "it_h_016",
    "text": "IL SEGRETO DEI SUOI OCCHI ARGENTINO",
    "hint": "Film premio Oscar",
    "language": "it",
    "difficulty": "hard",
    "category": "movie"
  },
  {
    "id": "it_h_017",
    "text": "LA SOCIETA DELLO SPETTACOLO MODERNO",
    "hint": "Concetto sociologico",
    "language": "it",
    "difficulty": "hard",
    "category": "philosophy"
  },
  {
    "id": "it_h_018",
    "text": "IL PROCESSO DI FRANZ KAFKA",
    "hint": "Romanzo inquietante",
    "language": "it",
    "difficulty": "hard",
    "category": "literature"
  },
  {
    "id": "it_h_019",
    "text": "IL GRANDE DITTATORE DI CHAPLIN",
    "hint": "Film satirico",
    "language": "it",
    "difficulty": "hard",
    "category": "movie"
  },
  {
    "id": "it_h_020",
    "text": "LA CASA DEGLI SPIRITI DI ALLENDE",
    "hint": "Romanzo sudamericano",
    "language": "it",
    "difficulty": "hard",
    "category": "literature"
  },
  {
    "id": "it_h_021",
    "text": "LA RIVOLUZIONE INDUSTRIALE EUROPEA",
    "hint": "Evento storico",
    "language": "it",
    "difficulty": "hard",
    "category": "history"
  },
  {
    "id": "it_h_022",
    "text": "LA NASCITA DELLA TRAGEDIA DI NIETZSCHE",
    "hint": "Opera filosofica",
    "language": "it",
    "difficulty": "hard",
    "category": "philosophy"
  },
  {
    "id": "it_h_023",
    "text": "IL SIGNIFICATO DELLA VITA UMANA",
    "hint": "Tema filosofico",
    "language": "it",
    "difficulty": "hard",
    "category": "philosophy"
  },
  {
    "id": "it_h_024",
    "text": "LA DIVINA COMMEDIA DI DANTE ALIGHIERI",
    "hint": "Opera medievale",
    "language": "it",
    "difficulty": "hard",
    "category": "literature"
  },
  {
    "id": "it_h_025",
    "text": "IL PENSIERO LATERALE DI DE BONO",
    "hint": "Metodo creativo",
    "language": "it",
    "difficulty": "hard",
    "category": "philosophy"
  },
  {
    "id": "it_h_026",
    "text": "LA STRADA MENO PERCORSA DA FROST",
    "hint": "Poesia americana",
    "language": "it",
    "difficulty": "hard",
    "category": "literature"
  },
  {
    "id": "it_h_027",
    "text": "IL CORAGGIO DI CAMBIARE LE COSE",
    "hint": "Tema motivazionale",
    "language": "it",
    "difficulty": "hard",
    "category": "abstract"
  },
  {
    "id": "it_h_028",
    "text": "LA MEMORIA DEL PASSATO E DEL FUTURO",
    "hint": "Tema esistenziale",
    "language": "it",
    "difficulty": "hard",
    "category": "abstract"
  },
  {
    "id": "it_h_029",
    "text": "IL SENSO DELLA MISURA NELLA VITA",
    "hint": "Riflessione morale",
    "language": "it",
    "difficulty": "hard",
    "category": "abstract"
  },
  {
    "id": "it_h_030",
    "text": "LA PERCEZIONE DEL TEMPO E DELLO SPAZIO",
    "hint": "Concetto filosofico",
    "language": "it",
    "difficulty": "hard",
    "category": "philosophy"
  }
]